<?xml version="1.0" encoding="UTF-8" ?>
<!DOCTYPE mapper PUBLIC "-//mybatis.org//DTD Mapper 3.0//EN" "http://mybatis.org/dtd/mybatis-3-mapper.dtd">
<mapper namespace="com.thinkgem.jeesite.modules.sub.dao.PQianggouDao">
    
	<sql id="pQianggouColumns">
		a.id AS "id",
		a.title AS "title",
		a.total_amount AS "totalAmount",
		a.click_url AS "clickUrl",
		a.category_name AS "categoryName",
		a.zk_final_price AS "zkFinalPrice",
		a.start_time AS "starttime",
		a.end_time AS "endtime",
		a.sold_num AS "soldNum",
		a.reserve_price AS "reservePrice",
		a.pic_url AS "picUrl",
		a.type AS "type",
		a.num_iid AS "numiid"
	</sql>
	
	<sql id="pQianggouJoins">
	</sql>
    
	<select id="get" resultType="com.thinkgem.jeesite.modules.sub.entity.PQianggou">
		SELECT 
			<include refid="pQianggouColumns"/>
		FROM p_qianggou a WHERE a.num_iid = #{numiid}
	</select>
	
	<select id="findList" resultType="com.thinkgem.jeesite.modules.sub.entity.PQianggou" parameterType="com.thinkgem.jeesite.modules.sub.entity.LimitEntity">
		SELECT 
			<include refid="pQianggouColumns"/>
		FROM p_qianggou a limit #{page},20
	</select>
	
	<select id="findListByTitle" resultType="com.thinkgem.jeesite.modules.sub.entity.PQianggou" parameterType="com.thinkgem.jeesite.modules.sub.entity.LimitEntity">
		SELECT 
			<include refid="pQianggouColumns"/>
		FROM p_qianggou a where LOCATE(#{title},a.title)>0 limit #{page},20
	</select>
	
</mapper>